src/_version.py
src/bootstrap.py
src/jobs.py
src/main.py
src/runtime.py
src/schemas.py
src/tool_index.py
src/validator_registry.py
src/validators.py
src/managers/client_manager.py
src/managers/connection_manager.py
src/managers/device_manager.py
src/managers/event_manager.py
src/managers/firewall_manager.py
src/managers/hotspot_manager.py
src/managers/network_manager.py
src/managers/qos_manager.py
src/managers/routing_manager.py
src/managers/stats_manager.py
src/managers/system_manager.py
src/managers/traffic_route_manager.py
src/managers/usergroup_manager.py
src/managers/vpn_manager.py
src/tools/clients.py
src/tools/config.py
src/tools/devices.py
src/tools/events.py
src/tools/firewall.py
src/tools/hotspot.py
src/tools/network.py
src/tools/port_forwards.py
src/tools/qos.py
src/tools/routing.py
src/tools/stats.py
src/tools/system.py
src/tools/traffic_routes.py
src/tools/usergroups.py
src/tools/vpn.py
src/utils/config_helpers.py
src/utils/confirmation.py
src/utils/diagnostics.py
src/utils/lazy_tool_loader.py
src/utils/meta_tools.py
src/utils/permissions.py
src/utils/tool_loader.py
src/tools_manifest.json
src/config/config.yaml
unifi_network_mcp-0.5.1.data/data/share/unifi-network-mcp/.well-known/mcp-server.json
unifi_network_mcp-0.5.1.dist-info/METADATA
unifi_network_mcp-0.5.1.dist-info/WHEEL
unifi_network_mcp-0.5.1.dist-info/entry_points.txt
unifi_network_mcp-0.5.1.dist-info/licenses/LICENSE
unifi_network_mcp-0.5.1.dist-info/RECORD
