Metadata-Version: 2.4
Name: unifi-network-mcp
Version: 0.5.1
Summary: Unifi Network MCP Server
License-File: LICENSE
Requires-Python: >=3.13
Requires-Dist: aiohttp>=3.8.5
Requires-Dist: aiounifi>=88
Requires-Dist: jsonschema>=4.17.0
Requires-Dist: mcp[cli]>=1.23.0
Requires-Dist: omegaconf>=2.3.0
Requires-Dist: python-dotenv>=1.0.0
Requires-Dist: pyyaml>=6.0
Requires-Dist: typing-extensions>=4.4.0
